pyremto/Datatype.py
pyremto/Exceptions.py
pyremto/RemoteControl.py
pyremto/__init__.py
pyremto-1.0.4.dist-info/LICENSE
pyremto-1.0.4.dist-info/METADATA
pyremto-1.0.4.dist-info/WHEEL
pyremto-1.0.4.dist-info/top_level.txt
pyremto-1.0.4.dist-info/RECORD
