Metadata-Version: 2.1
Name: pyremto
Version: 1.0.4
Summary: Python Remote Tools: Manage Python scripts from anywhere
Home-page: https://www.pyremto.com
Download-URL: https://github.com/MatthiasKi/pyremto
Author: Matthias Kissel
Author-email: contact@pyremto.com
Classifier: Programming Language :: Python :: 3
Classifier: Operating System :: OS Independent
Requires-Python: >=3.6
License-File: LICENSE
Requires-Dist: qrcode (>=7.3.1)
Requires-Dist: Pillow (>=9.2.0)
Requires-Dist: requests (>=2.28.1)
Requires-Dist: matplotlib (>=3.6.1)
Requires-Dist: scikit-learn (>=1.1.2)
